{
  "generated_at": "2026-06-24T11:39:11Z",
  "sources": [
    {
      "source_key": "bkg_vg250",
      "source_name": "VG250 Verwaltungsgebiete 1:250 000",
      "provider": "Bundesamt fuer Kartographie und Geodaesie",
      "metadata_url": "https://gdz.bkg.bund.de/index.php/default/verwaltungsgebiete-1-250-000-stand-01-01-vg250-01-01.html",
      "download_url": "https://daten.gdz.bkg.bund.de/produkte/vg/vg250_ebenen_0101/aktuell/vg250_01-01.utm32s.gpkg.ebenen.zip",
      "file_name": "data/raw/bkg/vg250_01-01.utm32s.gpkg.ebenen.zip",
      "format": "zip",
      "license": "Datenlizenz Deutschland Namensnennung 2.0 / GeoNutzV",
      "attribution": "GeoBasis-DE / BKG",
      "http_status": 200,
      "resolved_download_url": "https://daten.gdz.bkg.bund.de/produkte/vg/vg250_ebenen_0101/aktuell/vg250_01-01.utm32s.gpkg.ebenen.zip",
      "content_type": "application/zip",
      "content_length": "72326773",
      "etag": "\"68a46517-44f9e75\"",
      "last_modified": "Tue, 19 Aug 2025 11:50:47 GMT",
      "downloaded_at": null,
      "file_size_bytes": 72326773,
      "sha256": "0a3c106a7537e1b47e97077d923c660e22510f73031463a420e7718c6f129e42",
      "valid_from": null,
      "valid_until": null,
      "validation_status": "validated",
      "integration_status": "pending",
      "notes": null,
      "raw_metadata": {}
    },
    {
      "source_key": "delfi_gtfs",
      "source_name": "Deutschlandweite Sollfahrplandaten (GTFS)",
      "provider": "DELFI e.V. / Mobidrom",
      "metadata_url": "https://www.mobilitaetsdaten.nrw/api/ckan/en/dataset/deutschlandweite-sollfahrplandaten-gtfs",
      "download_url": "https://mobi.nrw/gtfs-deutschland-gesamt.zip",
      "file_name": "data/raw/delfi/gtfs-deutschland-gesamt.zip",
      "format": "zip",
      "license": "CC BY 4.0",
      "attribution": "DELFI e.V.",
      "http_status": 200,
      "resolved_download_url": "https://www.opendata-oepnv.de/fileadmin/datasets/delfi/20260622_fahrplaene_gesamtdeutschland_gtfs.zip",
      "content_type": "application/zip",
      "content_length": "435515166",
      "etag": "\"6a38eba7-19f56f1e\"",
      "last_modified": "Mon, 22 Jun 2026 08:00:39 GMT",
      "downloaded_at": null,
      "file_size_bytes": 435515166,
      "sha256": "bb69c7e2c8d50e6f923e397f5d39a17c4e514cb6e4e258473cff65798b5b902e",
      "valid_from": "2026-06-06",
      "valid_until": "2026-12-12",
      "validation_status": "validated",
      "integration_status": "pending",
      "notes": null,
      "raw_metadata": {
        "record_counts": {
          "agency.txt": 1157,
          "calendar.txt": 28655,
          "calendar_dates.txt": 641436,
          "feed_info.txt": 1,
          "frequencies.txt": 21,
          "levels.txt": 11,
          "pathways.txt": 329997,
          "routes.txt": 29196,
          "shapes.txt": 10569800,
          "stop_times.txt": 45880781,
          "stops.txt": 545533,
          "transfers.txt": 1036849,
          "trips.txt": 2267786
        },
        "feed_publisher_name": "DELFI e.V.",
        "feed_publisher_url": "https://www.delfi.de",
        "feed_lang": "de",
        "feed_start_date": "20260606",
        "feed_end_date": "20261212",
        "feed_version": "2026-06-20T13:40:14",
        "feed_contact_email": "Delfi-Fahrplandaten@rms-consult.de",
        "feed_contact_url": "https://www.delfi.de",
        "valid_from": "20260606",
        "valid_until": "20261212"
      }
    },
    {
      "source_key": "geofabrik_germany_osm",
      "source_name": "Germany OpenStreetMap PBF",
      "provider": "Geofabrik GmbH / OpenStreetMap Contributors",
      "metadata_url": "https://download.geofabrik.de/europe/germany.html",
      "download_url": "https://download.geofabrik.de/europe/germany-latest.osm.pbf",
      "file_name": "data/raw/osm/germany-latest.osm.pbf",
      "format": "osm.pbf",
      "license": "ODbL 1.0",
      "attribution": "OpenStreetMap contributors, Geofabrik GmbH",
      "http_status": 200,
      "resolved_download_url": "https://ftp5.gwdg.de/pub/misc/openstreetmap/download.geofabrik.de/germany-latest.osm.pbf",
      "content_type": "application/octet-stream",
      "content_length": "4786474751",
      "etag": "\"6a3b4403-11d4bceff\"",
      "last_modified": "Wed, 24 Jun 2026 02:42:11 GMT",
      "downloaded_at": null,
      "file_size_bytes": 4786474751,
      "sha256": "d957290fe75a9f599ff3abd2a883328c58e0c67a1db332f15a11647e86d0e74d",
      "valid_from": null,
      "valid_until": null,
      "validation_status": "warning",
      "integration_status": "pending",
      "notes": "Geofabrik latest MD5 did not match downloaded redirect target; likely mirror/latest timing mismatch.",
      "raw_metadata": {
        "geofabrik_md5": "3196c1e372bb0131ae7deaa013954c63",
        "md5": "55ca10225c4403518e223e04dca4e74d"
      }
    }
  ]
}